stumpy/__init__.py
stumpy/aamp.py
stumpy/aamp_mmotifs.py
stumpy/aamp_motifs.py
stumpy/aamp_ostinato.py
stumpy/aamp_stimp.py
stumpy/aampdist.py
stumpy/aampdist_snippets.py
stumpy/aamped.py
stumpy/aampi.py
stumpy/cache.py
stumpy/chains.py
stumpy/config.py
stumpy/core.py
stumpy/floss.py
stumpy/gpu_aamp.py
stumpy/gpu_aamp_ostinato.py
stumpy/gpu_aamp_stimp.py
stumpy/gpu_aampdist.py
stumpy/gpu_mpdist.py
stumpy/gpu_ostinato.py
stumpy/gpu_stimp.py
stumpy/gpu_stump.py
stumpy/maamp.py
stumpy/maamped.py
stumpy/mmotifs.py
stumpy/motifs.py
stumpy/mparray.py
stumpy/mpdist.py
stumpy/mstump.py
stumpy/mstumped.py
stumpy/ostinato.py
stumpy/scraamp.py
stumpy/scrump.py
stumpy/snippets.py
stumpy/stamp.py
stumpy/stimp.py
stumpy/stomp.py
stumpy/stump.py
stumpy/stumped.py
stumpy/stumpi.py
stumpy-1.13.0.dist-info/LICENSE.txt
stumpy-1.13.0.dist-info/METADATA
stumpy-1.13.0.dist-info/WHEEL
stumpy-1.13.0.dist-info/top_level.txt
stumpy-1.13.0.dist-info/RECORD
