Metadata-Version: 2.1
Name: stumpy
Version: 1.13.0
Summary: A powerful and scalable library that can be used for a variety of time series data mining tasks
Author-email: "Sean M. Law" <seanmylaw@gmail.com>
Maintainer-email: "Sean M. Law" <seanmylaw@gmail.com>, Nima Sarajpoor <nimasarajpoor@gmail.com>
License: 3-clause BSD License
Project-URL: Homepage, https://github.com/TDAmeritrade/stumpy
Project-URL: Documentation, https://stumpy.readthedocs.io/en/latest/
Project-URL: Repository, https://github.com/TDAmeritrade/stumpy
Keywords: time series,matrix profile,motif,discord
Classifier: Development Status :: 3 - Alpha
Classifier: Intended Audience :: Science/Research
Classifier: Intended Audience :: Developers
Classifier: License :: OSI Approved :: BSD License
Classifier: Programming Language :: Python
Classifier: Topic :: Software Development
Classifier: Topic :: Scientific/Engineering
Classifier: Operating System :: Microsoft :: Windows
Classifier: Operating System :: POSIX
Classifier: Operating System :: Unix
Classifier: Operating System :: MacOS
Classifier: Programming Language :: Python :: 3.8
Requires-Python: >=3.8
License-File: LICENSE.txt
Requires-Dist: numpy>=1.21
Requires-Dist: scipy>=1.10
Requires-Dist: numba>=0.57.1
Provides-Extra: ci
Requires-Dist: pandas>=0.20.0; extra == "ci"
Requires-Dist: dask>=1.2.2; extra == "ci"
Requires-Dist: distributed>=1.28.1; extra == "ci"
Requires-Dist: coverage>=4.5.3; extra == "ci"
Requires-Dist: flake8>=3.7.7; extra == "ci"
Requires-Dist: flake8-docstrings>=1.5.0; extra == "ci"
Requires-Dist: black>=22.1.0; extra == "ci"
Requires-Dist: pytest>=4.4.1; extra == "ci"
Requires-Dist: isort>=5.11.0; extra == "ci"
Requires-Dist: tbb>=2019.5; platform_system == "Linux" and extra == "ci"
